py4pa/__init__.py
py4pa/data_manipulation.py
py4pa/email_helper.py
py4pa/log.py
py4pa/misc.py
py4pa/nlp.py
py4pa/ona.py
py4pa/sftp.py
py4pa/visier.py
py4pa/visualisation.py
py4pa-0.2.0.dist-info/LICENSE.txt
py4pa-0.2.0.dist-info/METADATA
py4pa-0.2.0.dist-info/WHEEL
py4pa-0.2.0.dist-info/top_level.txt
py4pa-0.2.0.dist-info/RECORD
