Metadata-Version: 2.1
Name: py4pa
Version: 0.2.0
Summary: Package of various helper modules to support various People Analytics projects
Author-email: Kevin Metherell <kevindickens@gmail.com>
License: MIT License
Project-URL: Homepage, https://py4pa.readthedocs.io/en/latest/
Project-URL: Documentation, https://py4pa.readthedocs.io/en/latest/
Project-URL: Repository, https://github.com/kammetherell/py4pa/
Project-URL: Issues, https://github.com/kammetherell/py4pa/issues
Classifier: Programming Language :: Python :: 3
Classifier: License :: OSI Approved :: MIT License
Requires-Python: >=3.6
License-File: LICENSE.txt
Requires-Dist: pandas
Requires-Dist: numpy
Requires-Dist: datetime
Requires-Dist: networkx
Requires-Dist: requests
Requires-Dist: bs4
Requires-Dist: urllib3
Requires-Dist: fake-useragent
Requires-Dist: pysftp
